incenp/__init__.py
incenp/bio/__init__.py
incenp/bio/modelling/__init__.py
incenp/bio/modelling/cc3d.py
incenp/bio/seq/__init__.py
incenp/bio/seq/databases.py
incenp/bio/seq/plasmidmap.py
incenp/bio/seq/seqtool.py
incenp/bio/seq/seqvault.py
incenp/bio/seq/usa.py
incenp/bio/seq/utils.py
incenp/bio/seq/vault.py
incenp/bio/seq/wrappers.py
incenp.bioutils-0.2.0.dist-info/AUTHORS
incenp.bioutils-0.2.0.dist-info/COPYING
incenp.bioutils-0.2.0.dist-info/METADATA
incenp.bioutils-0.2.0.dist-info/WHEEL
incenp.bioutils-0.2.0.dist-info/entry_points.txt
incenp.bioutils-0.2.0.dist-info/top_level.txt
incenp.bioutils-0.2.0.dist-info/RECORD
