Metadata-Version: 2.1
Name: incenp.bioutils
Version: 0.2.0
Summary: Incenp.org’s utilities for computational biology
Home-page: UNKNOWN
Author: Damien Goutte-Gattat
Author-email: dgouttegattat@incenp.org
License: UNKNOWN
Platform: UNKNOWN
Classifier: Development Status :: 3 - Alpha
Classifier: Environment :: Console
Classifier: License :: OSI Approved :: GNU General Public License v3 or later (GPLv3+)
Classifier: Programming Language :: Python :: 3
Requires-Dist: biopython
Requires-Dist: click
Requires-Dist: click-shell
Provides-Extra: plasmm
Requires-Dist: reportlab ; extra == 'plasmm'
